{
	"user": "Danix43",
	"repo": "SampWarSystemClanClr",
	"entry": "gamemodes/base.pwn",
	"output": "gamemodes/base.amx",
	"local": true,
	"dependencies": [
		"sampctl/samp-stdlib",
		"pBlueG/SA-MP-MySQL",
		"maddinat0r/sscanf",
		"YashasSamaga/I-ZCMD"
	],
	"builds": [
		{
			"name": "main",
			"includes": [
				"legacy"
			]
		}
	],
	"runtime": {
		"hostname": "War Between Mafia - Clan CLR",
		"rcon": false,
		"port": 7777,
		"language": "Romana / Tiganeasca",
		"mapname": "Peris / Ferentexas",
		"maxplayers": 20,
		"rcon_password": "danix1923",
		"weburl": "discord.gg/SE5yvJyX5C",
		"announce": false,
		"filterscripts": [
			"orders",
			"mafia"
		],
		"plugins": [
			"SA-MP-MySQL",
			"sscanf",
			"izcmd",
			"a_zone"
		]
	}
}